LICENSE
MANIFEST.in
README.txt
setup.cfg
setup.py
bin/ForceBalance
bin/ForceBalance.py
bin/MakeInputFile.py
bin/TidyOutput
bin/filecnv.py
doc/DoxygenLayout.xml
doc/ForceBalance-Manual.pdf
doc/add-tabs.py
doc/doxygen.cfg
doc/doxypy.py
doc/glossary.txt
doc/header.tex
doc/installation.txt
doc/introduction.txt
doc/make-option-index.py
doc/makedocumentation.py
doc/roadmap.txt
doc/tutorial.txt
doc/usage.txt
doc/Images/ForceBalance.pdf
doc/Images/ForceBalanceLogo_sm.png
doc/Images/convert-images.txt
doc/Images/cycle.png
doc/Images/cycle_sm.png
doc/Images/flowchart.png
doc/Images/flowchart_sm.png
doc/Images/interactions.png
doc/Images/interactions_sm.png
doc/Images/ladder.png
doc/Images/ladder_sm.png
doc/callgraph/CallGraph.py
doc/callgraph/Run_To_Make_Cool_Picture.sh
ext/molfile_plugin/LICENSE
ext/molfile_plugin/Makefile
ext/molfile_plugin/dcdplugin.c
ext/molfile_plugin/dcdplugin_s.c
ext/molfile_plugin/endianswap.h
ext/molfile_plugin/fastio.h
ext/molfile_plugin/largefiles.h
ext/molfile_plugin/namdbinplugin.c
ext/molfile_plugin/include/import_graphics_plugin.h
ext/molfile_plugin/include/molfile_plugin.h
ext/molfile_plugin/include/vmdconio.h
ext/molfile_plugin/include/vmdplugin.h
forcebalance.egg-info/PKG-INFO
forcebalance.egg-info/SOURCES.txt
forcebalance.egg-info/dependency_links.txt
forcebalance.egg-info/top_level.txt
src/AUTHORS
src/Mol2.py
src/PDB.py
src/PT.py
src/__init__.py
src/_version.py
src/abinitio.py
src/abinitio_internal.py
src/amberio.py
src/binding.py
src/chemistry.py
src/counterpoise.py
src/custom_io.py
src/engine.py
src/evaluator_io.py
src/finite_difference.py
src/forcefield.py
src/gmxio.py
src/hessian.py
src/hydration.py
src/interaction.py
src/leastsq.py
src/lipid.py
src/liquid.py
src/molecule.py
src/moments.py
src/nifty.py
src/objective.py
src/openmmio.py
src/opt_geo_target.py
src/optimizer.py
src/output.py
src/parser.py
src/psi4io.py
src/qchemio.py
src/quantity.py
src/readfrq.py
src/recharge_io.py
src/smirnoff_hack.py
src/smirnoffio.py
src/target.py
src/thermo.py
src/tinkerio.py
src/torsion_profile.py
src/vibration.py
src/data/data.csv.template
src/data/gmxprefix.bash
src/data/md_chain.py
