Metadata-Version: 2.1
Name: forcebalance
Version: 1.9.5
Summary: Automated force field optimization.
Home-page: https://simtk.org/home/forcebalance
Download-URL: https://simtk.org/home/forcebalance
Author: Lee-Ping Wang
Author-email: leeping@ucdavis.edu
License: BSD 2.0
Platform: Linux
License-File: LICENSE
